midi_wrapper/__init__.py
midi_wrapper/midi_device.py
midi_wrapper/midi_input.py
midi_wrapper/midi_menu.py
midi_wrapper_SnooperXP-0.0.5.dist-info/LICENSE
midi_wrapper_SnooperXP-0.0.5.dist-info/METADATA
midi_wrapper_SnooperXP-0.0.5.dist-info/WHEEL
midi_wrapper_SnooperXP-0.0.5.dist-info/top_level.txt
midi_wrapper_SnooperXP-0.0.5.dist-info/RECORD
