Metadata-Version: 2.1
Name: midi-wrapper-SnooperXP
Version: 0.0.5
Summary: A package that wraps Pygame midi for simplified use
Home-page: https://github.com/SnooperXP/neos-vr-midi
Author: Snooper Xp
Author-email: snooperxp@gmail.com
License: UNKNOWN
Platform: UNKNOWN
Classifier: Programming Language :: Python :: 3
Classifier: License :: OSI Approved :: MIT License
Classifier: Operating System :: OS Independent
Requires-Python: >=3.6
